starsystem/__init__.py
starsystem/mission.py
starsystem/mission_types.py
starsystem/reward_system.py
starsystem/starsystem_mcp.py
starsystem-1.0.0.dist-info/licenses/LICENSE
starsystem-1.0.0.dist-info/METADATA
starsystem-1.0.0.dist-info/WHEEL
starsystem-1.0.0.dist-info/entry_points.txt
starsystem-1.0.0.dist-info/top_level.txt
starsystem-1.0.0.dist-info/RECORD
