Metadata-Version: 2.4
Name: starsystem
Version: 1.0.0
Summary: STARSYSTEM - Complete compound intelligence ecosystem with master help system
Home-page: https://github.com/sancovp/starsystem
Author: Isaac
License: GNOSYS Personal Builder License (GPBL) v1.0
Keywords: ai llm mcp compound-intelligence starsystem heaven starlog giint carton
Classifier: Development Status :: 4 - Beta
Classifier: Intended Audience :: Developers
Classifier: Topic :: Software Development :: Libraries
Classifier: Programming Language :: Python :: 3
Classifier: Programming Language :: Python :: 3.9
Classifier: Programming Language :: Python :: 3.10
Classifier: Programming Language :: Python :: 3.11
Requires-Python: >=3.9
License-File: LICENSE
Requires-Dist: fastmcp>=2.0.0
Dynamic: author
Dynamic: classifier
Dynamic: description
Dynamic: description-content-type
Dynamic: home-page
Dynamic: keywords
Dynamic: license
Dynamic: license-file
Dynamic: requires-dist
Dynamic: requires-python
Dynamic: summary
